FSM_Practice/FSM_one-hot_encoding_Counter.v
// FSM 관련 연습 진행
// FSM을 verilog로 작성할때 어떻게 하는지 알아봅시다.

// One-Hot Encoding 방식을 사용하여 작성

// Verilog 로 작성하는 5-way counter
// inc가 high이면 앞으로 진행, inc가 low이면 뒤로 진행

// 코드 시작

// Coding Module Header

module cnt5_o(cnt, clk, rb, inc);
	input clk, rb, inc;
	output [4:0] cnt;

	parameter zero = 5'b00001; // parameter: 베릴로그에서 상수를 정의할 때 사용
	parameter one = 5'b00010;
	parameter two = 5'b00100;
	parameter three = 5'b01000;
	parameter four = 5'b10000;

	// Sequential Circuits 부분
	reg [4:0] cnt;
	reg [4:0] next_cnt;
	
	// 아래 부분은 Binary나 One-Hot이나 같은 모습을 보여줌.

	always @ (posedge clk or negedge rb) begin
		if (rb == 1'b0) cnt <= zero;
		else cnt <= next_cnt;
	end

	// Combinational Circuit 부분
	always @ (inc or cnt) begin
		case ({cnt, inc}) // {}를 이용하여 결합형식으로 사용할 수 있음
			{zero, 1'b0}: next_cnt <= four;
			{one, 1'b0}: next_cnt <= zero;
			{two, 1'b0}: next_cnt <= one;
			{three, 1'b0}: next_cnt <= two;
			{four, 1'b0}: next_cnt <= three;
			
			{zero, 1'b1}: next_cnt <= one;
			{one, 1'b1}: next_cnt <= two;
			{two, 1'b1}: next_cnt <= three;
			{three, 1'b1}: next_cnt <= four;
			{four, 1'b1}: next_cnt <= zero;

			default: next_cnt <= 3'bx;
		endcase
	end
endmodule

FSM_Practice/FSM_binary_encoding_Counter.v
// FSM 관련 연습 진행
// FSM을 verilog로 작성할때 어떻게 하는지 알아봅시다.

// 일단은 Binary Encoding 방식을 사용하여 작성

// Verilog 로 작성하는 5-way counter
// inc가 high이면 앞으로 진행, inc가 low이면 뒤로 진행

// 코드 시작

// Coding Module Header

module cnt5_b(cnt, clk, rb, inc);
	input clk, rb, inc;
	output [2:0] cnt;

	parameter zero = 3'b000; // parameter: 베릴로그에서 상수를 정의할 때 사용
	parameter one = 3'b001;
	parameter two = 3'b010;
	parameter three = 3'b011;
	parameter four = 3'b100;

	// Sequential Circuits 부분
	reg [2:0] cnt;
	reg [2:0] next_cnt;

	always @ (posedge clk or negedge rb) begin
		if (rb == 1'b0) cnt <= zero;
		else cnt <= next_cnt;
	end

	// Combinational Circuit 부분
	always @ (inc or cnt) begin
		case ({cnt, inc}) // {}를 이용하여 결합형식으로 사용할 수 있음
			{zero, 1'b0}: next_cnt <= four;
			{one, 1'b0}: next_cnt <= zero;
			{two, 1'b0}: next_cnt <= one;
			{three, 1'b0}: next_cnt <= two;
			{four, 1'b0}: next_cnt <= three;
			
			{zero, 1'b1}: next_cnt <= one;
			{one, 1'b1}: next_cnt <= two;
			{two, 1'b1}: next_cnt <= three;
			{three, 1'b1}: next_cnt <= four;
			{four, 1'b1}: next_cnt <= zero;

			default: next_cnt <= 3'bx;
		endcase
	end
endmodule

FSM_Practice/TB_FSM_Counter.v
// Counter의 테스트벤치

module tb_cnt5;
	reg clk, rb, inc;
	wire [2:0] c_b;
	wire [4:0] c_o;
	
	cnt5_b counterBin(c_b, clk, rb, inc);
	cnt5_o counterOneHot(c_o, clk, rb, inc);

	always begin
		clk = 1; #5; clk = 0; #5;
	end

	initial begin
		$dumpfile("FSMvcd.vcd");
		$dumpvars(-1, counterBin);
		$dumpvars(-1, counterOneHot);
		inc = 1; rb = 0; #15; rb = 1; #60;
		inc = 0; #70;
		$finish;
	end
endmodule

FSM_Practice/FSMvcd.vcd
$date
	Mon Jul 12 01:05:57 2021
$end
$version
	Icarus Verilog
$end
$timescale
	1s
$end
$scope module tb_cnt5 $end
$scope module counterBin $end
$var wire 1 ! clk $end
$var wire 1 " inc $end
$var wire 1 # rb $end
$var reg 3 $ cnt [2:0] $end
$var reg 3 % next_cnt [2:0] $end
$upscope $end
$upscope $end
$scope module tb_cnt5 $end
$scope module counterOneHot $end
$var wire 1 ! clk $end
$var wire 1 " inc $end
$var wire 1 # rb $end
$var reg 5 & cnt [4:0] $end
$var reg 5 ' next_cnt [4:0] $end
$upscope $end
$upscope $end
$enddefinitions $end
#0
$dumpvars
b10 '
b1 &
b1 %
b0 $
0#
1"
1!
$end
#5
0!
#10
1!
#15
0!
1#
#20
b10 %
b100 '
b1 $
b10 &
1!
#25
0!
#30
b1000 '
b11 %
b100 &
b10 $
1!
#35
0!
#40
b100 %
b10000 '
b11 $
b1000 &
1!
#45
0!
#50
b1 '
b0 %
b10000 &
b100 $
1!
#55
0!
#60
b1 %
b10 '
b0 $
b1 &
1!
#65
0!
#70
b100 '
b10 %
b10 &
b1 $
1!
#75
b0 %
b1 '
0!
0"
#80
b100 %
b10000 '
b0 $
b1 &
1!
#85
0!
#90
b1000 '
b11 %
b10000 &
b100 $
1!
#95
0!
#100
b10 %
b100 '
b11 $
b1000 &
1!
#105
0!
#110
b10 '
b1 %
b100 &
b10 $
1!
#115
0!
#120
b0 %
b1 '
b1 $
b10 &
1!
#125
0!
#130
b10000 '
b100 %
b1 &
b0 $
1!
#135
0!
#140
b11 %
b1000 '
b100 $
b10000 &
1!
